weather_app/__init__.py
weather_app/api.py
weather_app/app.py
weather_app/render.py
smhpy-0.1.dist-info/LICENSE
smhpy-0.1.dist-info/METADATA
smhpy-0.1.dist-info/WHEEL
smhpy-0.1.dist-info/entry_points.txt
smhpy-0.1.dist-info/top_level.txt
smhpy-0.1.dist-info/RECORD
