Metadata-Version: 2.1
Name: smhpy
Version: 0.1
Summary: My first package.
Home-page: https://github.com/simonpf/weatherapp
Author: Simon Pfreundschuh
Author-email: simon.pfreundschuh@chalmers.se
License: UNKNOWN
Platform: UNKNOWN
Requires-Python: >=3.6
Requires-Dist: numpy
